chargecloudapi/__init__.py
chargecloudapi/api.py
chargecloudapi/models.py
pychargecloud-0.2.6.dist-info/licenses/LICENSE.md
pychargecloud-0.2.6.dist-info/METADATA
pychargecloud-0.2.6.dist-info/WHEEL
pychargecloud-0.2.6.dist-info/top_level.txt
pychargecloud-0.2.6.dist-info/RECORD
