Metadata-Version: 2.4
Name: pychargecloud
Version: 0.2.6
Summary: Access public ev charger information via chargecloud.de
Author-email: functionpointer <suspendfunction@gmail.com>
License: GNU General Public License v3 or later (GPLv3+)
Project-URL: homepage, https://github.com/functionpointer/pychargecloud
Classifier: Programming Language :: Python :: 3.10
Classifier: License :: OSI Approved :: GNU General Public License v3 or later (GPLv3+)
Requires-Python: >=3.10
License-File: LICENSE.md
Requires-Dist: aiohttp
Requires-Dist: yarl
Requires-Dist: pydantic<3.0.0,>=1.0.0
Dynamic: license-file
